email_scraper/__init__.py
email_scraper/scrape.py
email_scraper-0.5.dist-info/LICENSE
email_scraper-0.5.dist-info/METADATA
email_scraper-0.5.dist-info/WHEEL
email_scraper-0.5.dist-info/top_level.txt
email_scraper-0.5.dist-info/zip-safe
email_scraper-0.5.dist-info/RECORD
