Metadata-Version: 2.1
Name: email-scraper
Version: 0.5
Summary: Simple utility to extract email addresses from HTML, including obfuscated email addresses
Home-page: https://github.com/kichik/email-scraper
Author: Amir Szekely
Author-email: kichik@gmail.com
License: MIT
Keywords: email scraping web obfuscate
Platform: UNKNOWN
Classifier: Development Status :: 4 - Beta
Classifier: Programming Language :: Python
Classifier: License :: OSI Approved :: MIT License
Classifier: Topic :: Communications :: Email
Classifier: Topic :: Text Processing :: Markup :: HTML
Requires-Dist: tlds
